{
	"info": {
		"_postman_id": "3d75a71f-601b-4c1c-91f8-7917822d57ae",
		"name": "DMS: Documents Management Solution",
		"schema": "https://schema.getpostman.com/json/collection/v2.1.0/collection.json"
	},
	"item": [
		{
			"name": "Documents",
			"item": [
				{
					"name": "Upload File (PreSigned URL)",
					"item": [
						{
							"name": "Success scenarios",
							"item": [
								{
									"name": "Upload Insurance Documents (Generate URLs)",
									"request": {
										"method": "POST",
										"header": [],
										"body": {
											"mode": "raw",
											"raw": "{\n    \"initiatorsystemcode\": \"ABC_WEB_APP\",\n    \"requestorid\": \"REQUESTOR_COGNITO_ID_1\",\n    \"files\": [\n        {\n            \"documentownerid\": \"DOC_OWNER_ID_1\",\n            \"documentformat\": \"PDF\",\n            \"documentsize\": 1048576,\n            \"documentcategory\": \"INSURANCE_CLAIM\"\n        },\n        {\n            \"documentownerid\": \"DOC_OWNER_ID_1\",\n            \"documentformat\": \"PDF\",\n            \"documentsize\": 1048576,\n            \"documentcategory\": \"PRE-AUTH-REQUEST\",\n            \"metadata\": {\n              \"documentnumber\": \"123456789012\",\n              \"issuedate\": \"1596421138000\",\n              \"expirydate\": \"7596421138000\",\n              \"issuedby\": \"Government of India\",\n              \"issuedto\": \"Akash Gupta\"\n            }\n        }\n    ]\n}\n",
											"options": {
												"raw": {
													"language": "json"
												}
											}
										},
										"url": {
											"raw": "{{API_GATEWAY_URL}}/document/upload",
											"host": [
												"{{API_GATEWAY_URL}}"
											],
											"path": [
												"document",
												"upload"
											]
										}
									},
									"response": []
								},
								{
									"name": "Upload Billing Documents (Generate URLs)",
									"request": {
										"method": "POST",
										"header": [],
										"body": {
											"mode": "raw",
											"raw": "{\n    \"initiatorsystemcode\": \"ABC_WEB_APP\",\n    \"requestorid\": \"REQUESTOR_COGNITO_ID_1\",\n    \"files\": [\n        {\n            \"documentownerid\": \"DOC_OWNER_ID_1\",\n            \"documentformat\": \"PDF\",\n            \"documentsize\": 1048576,\n            \"documentcategory\": \"BILLING_STATEMENT\"\n        },\n        {\n            \"documentownerid\": \"DOC_OWNER_ID_1\",\n            \"documentformat\": \"PDF\",\n            \"documentsize\": 1048576,\n            \"documentcategory\": \"PAYMENT_RECEIPT\",\n            \"metadata\": {\n              \"documentnumber\": \"123456789012\",\n              \"issuedate\": \"1596421138000\",\n              \"expirydate\": \"7596421138000\",\n              \"issuedby\": \"Government of India\",\n              \"issuedto\": \"Akash Gupta\"\n            }\n        }\n    ]\n}\n",
											"options": {
												"raw": {
													"language": "json"
												}
											}
										},
										"url": {
											"raw": "{{API_GATEWAY_URL}}/document/upload",
											"host": [
												"{{API_GATEWAY_URL}}"
											],
											"path": [
												"document",
												"upload"
											]
										}
									},
									"response": []
								},
								{
									"name": "Upload Consent Forms (Generate URLs)",
									"request": {
										"method": "POST",
										"header": [],
										"body": {
											"mode": "raw",
											"raw": "{\n    \"initiatorsystemcode\": \"ABC_WEB_APP\",\n    \"requestorid\": \"REQUESTOR_COGNITO_ID_1\",\n    \"files\": [\n        {\n            \"documentownerid\": \"DOC_OWNER_ID_1\",\n            \"documentformat\": \"PDF\",\n            \"documentsize\": 1048576,\n            \"documentcategory\": \"INFORMED_CONSENT_FOR_PROCEDURE\"\n        },\n        {\n            \"documentownerid\": \"DOC_OWNER_ID_1\",\n            \"documentformat\": \"PDF\",\n            \"documentsize\": 1048576,\n            \"documentcategory\": \"CONSENT_FOR_MEDICAL_INFO_RELEASE\",\n            \"metadata\": {\n              \"documentnumber\": \"123456789012\",\n              \"issuedate\": \"1596421138000\",\n              \"expirydate\": \"7596421138000\",\n              \"issuedby\": \"Government of India\",\n              \"issuedto\": \"Akash Gupta\"\n            }\n        },\n        {\n            \"documentownerid\": \"DOC_OWNER_ID_1\",\n            \"documentformat\": \"PDF\",\n            \"documentsize\": 1048576,\n            \"documentcategory\": \"CONSENT_FOR_RESEARCH_PARTICIPATION\",\n            \"metadata\": {\n              \"documentnumber\": \"123456789012\",\n              \"issuedate\": \"1596421138000\",\n              \"expirydate\": \"7596421138000\",\n              \"issuedby\": \"Government of India\",\n              \"issuedto\": \"Akash Gupta\"\n            }\n        }\n    ]\n}\n",
											"options": {
												"raw": {
													"language": "json"
												}
											}
										},
										"url": {
											"raw": "{{API_GATEWAY_URL}}/document/upload",
											"host": [
												"{{API_GATEWAY_URL}}"
											],
											"path": [
												"document",
												"upload"
											]
										}
									},
									"response": []
								},
								{
									"name": "Upload via Pre-Signed URL",
									"request": {
										"method": "PUT",
										"header": [
											{
												"key": "Content-Type",
												"value": "application/pdf",
												"type": "default"
											}
										],
										"body": {
											"mode": "file",
											"file": {
												"src": ""
											}
										},
										"url": {
											"raw": "https://tbd.s3.us-east-1.amazonaws.com/tbd",
											"protocol": "https",
											"host": [
												"tbd",
												"s3",
												"us-east-1",
												"amazonaws",
												"com"
											],
											"path": [
												"tbd"
											]
										}
									},
									"response": []
								}
							]
						},
						{
							"name": "Failure scenarios",
							"item": [
								{
									"name": "Failure: Missed required parameter (initiatorSystemCode)",
									"request": {
										"method": "POST",
										"header": [],
										"body": {
											"mode": "raw",
											"raw": "{\n    \"requestorid\": \"PROVIDER_COGNITO_ID_2\",\n    \"files\": [\n        {\n            \"documentownerid\": \"PROVIDER_COGNITO_ID_2\",\n            \"documentformat\": \"PNG\",\n            \"documentsize\": 1048576,\n            \"documentcategory\": \"PROFESSIONAL_PHOTO\"\n        }\n    ]\n}\n",
											"options": {
												"raw": {
													"language": "json"
												}
											}
										},
										"url": {
											"raw": "{{API_GATEWAY_URL}}/document/upload",
											"host": [
												"{{API_GATEWAY_URL}}"
											],
											"path": [
												"document",
												"upload"
											]
										}
									},
									"response": []
								},
								{
									"name": "Failure: Missed required parameter (requestorId)",
									"request": {
										"method": "POST",
										"header": [],
										"body": {
											"mode": "raw",
											"raw": "{\n    \"initiatorsystemcode\": \"ABC_WEB_APP\",\n    \"files\": [\n        {\n            \"documentownerid\": \"PROVIDER_COGNITO_ID_2\",\n            \"documentformat\": \"PNG\",\n            \"documentsize\": 1048576,\n            \"documentcategory\": \"PROFESSIONAL_PHOTO\"\n        }\n    ]\n}\n",
											"options": {
												"raw": {
													"language": "json"
												}
											}
										},
										"url": {
											"raw": "{{API_GATEWAY_URL}}/document/upload",
											"host": [
												"{{API_GATEWAY_URL}}"
											],
											"path": [
												"document",
												"upload"
											]
										}
									},
									"response": []
								},
								{
									"name": "Failure: Missed required parameter (files)",
									"request": {
										"method": "POST",
										"header": [],
										"body": {
											"mode": "raw",
											"raw": "{\n    \"initiatorsystemcode\": \"ABC_WEB_APP\",\n    \"requestorid\": \"PROVIDER_COGNITO_ID_2\"\n}\n",
											"options": {
												"raw": {
													"language": "json"
												}
											}
										},
										"url": {
											"raw": "{{API_GATEWAY_URL}}/document/upload",
											"host": [
												"{{API_GATEWAY_URL}}"
											],
											"path": [
												"document",
												"upload"
											]
										}
									},
									"response": []
								},
								{
									"name": "Failure: Missed required parameter (documentOwnerId)",
									"request": {
										"method": "POST",
										"header": [],
										"body": {
											"mode": "raw",
											"raw": "{\n    \"initiatorsystemcode\": \"ABC_WEB_APP\",\n    \"requestorid\": \"PROVIDER_COGNITO_ID_2\",\n    \"files\": [\n        {\n            \"documentformat\": \"PNG\",\n            \"documentsize\": 1048576,\n            \"documentcategory\": \"PROFESSIONAL_PHOTO\"\n        }\n    ]\n}\n",
											"options": {
												"raw": {
													"language": "json"
												}
											}
										},
										"url": {
											"raw": "{{API_GATEWAY_URL}}/document/upload",
											"host": [
												"{{API_GATEWAY_URL}}"
											],
											"path": [
												"document",
												"upload"
											]
										}
									},
									"response": []
								},
								{
									"name": "Failure: Missed required parameter (documentFormat)",
									"request": {
										"method": "POST",
										"header": [],
										"body": {
											"mode": "raw",
											"raw": "{\n    \"initiatorsystemcode\": \"ABC_WEB_APP\",\n    \"requestorid\": \"PROVIDER_COGNITO_ID_2\",\n    \"files\": [\n        {\n            \"documentownerid\": \"PROVIDER_COGNITO_ID_2\",\n            \"documentsize\": 1048576,\n            \"documentcategory\": \"PROFESSIONAL_PHOTO\"\n        }\n    ]\n}\n",
											"options": {
												"raw": {
													"language": "json"
												}
											}
										},
										"url": {
											"raw": "{{API_GATEWAY_URL}}/document/upload",
											"host": [
												"{{API_GATEWAY_URL}}"
											],
											"path": [
												"document",
												"upload"
											]
										}
									},
									"response": []
								},
								{
									"name": "Failure: Missed required parameter (documentSize)",
									"request": {
										"method": "POST",
										"header": [],
										"body": {
											"mode": "raw",
											"raw": "{\n    \"initiatorsystemcode\": \"ABC_WEB_APP\",\n    \"requestorid\": \"PROVIDER_COGNITO_ID_2\",\n    \"files\": [\n        {\n            \"documentownerid\": \"PROVIDER_COGNITO_ID_2\",\n            \"documentformat\": \"PNG\",\n            \"documentcategory\": \"PROFESSIONAL_PHOTO\"\n        }\n    ]\n}\n",
											"options": {
												"raw": {
													"language": "json"
												}
											}
										},
										"url": {
											"raw": "{{API_GATEWAY_URL}}/document/upload",
											"host": [
												"{{API_GATEWAY_URL}}"
											],
											"path": [
												"document",
												"upload"
											]
										}
									},
									"response": []
								},
								{
									"name": "Failure: Missed required parameter (documentCategory)",
									"request": {
										"method": "POST",
										"header": [],
										"body": {
											"mode": "raw",
											"raw": "{\n    \"initiatorsystemcode\": \"ABC_WEB_APP\",\n    \"requestorid\": \"PROVIDER_COGNITO_ID_2\",\n    \"files\": [\n        {\n            \"documentownerid\": \"PROVIDER_COGNITO_ID_2\",\n            \"documentformat\": \"PNG\",\n            \"documentsize\": 1048576\n        }\n    ]\n}",
											"options": {
												"raw": {
													"language": "json"
												}
											}
										},
										"url": {
											"raw": "{{API_GATEWAY_URL}}/document/upload",
											"host": [
												"{{API_GATEWAY_URL}}"
											],
											"path": [
												"document",
												"upload"
											]
										}
									},
									"response": []
								},
								{
									"name": "Failure: Not Allowed parameter value (initiatorSystemCode)",
									"request": {
										"method": "POST",
										"header": [],
										"body": {
											"mode": "raw",
											"raw": "{\n    \"initiatorsystemcode\": \"TBD\",\n    \"requestorid\": \"PROVIDER_COGNITO_ID_2\",\n    \"files\": [\n        {\n            \"documentownerid\": \"PROVIDER_COGNITO_ID_2\",\n            \"documentformat\": \"PDF\",\n            \"documentsize\": 1048576,\n            \"documentcategory\": \"PROFESSIONAL_PHOTO\"\n        }\n    ]\n}",
											"options": {
												"raw": {
													"language": "json"
												}
											}
										},
										"url": {
											"raw": "{{API_GATEWAY_URL}}/document/upload",
											"host": [
												"{{API_GATEWAY_URL}}"
											],
											"path": [
												"document",
												"upload"
											]
										}
									},
									"response": []
								},
								{
									"name": "Failure: Not Allowed parameter value (documentFormat)",
									"request": {
										"method": "POST",
										"header": [],
										"body": {
											"mode": "raw",
											"raw": "{\n    \"initiatorsystemcode\": \"ABC_WEB_APP\",\n    \"requestorid\": \"PROVIDER_COGNITO_ID_2\",\n    \"files\": [\n        {\n            \"documentownerid\": \"PROVIDER_COGNITO_ID_2\",\n            \"documentformat\": \"TBD\",\n            \"documentsize\": 1048576,\n            \"documentcategory\": \"PROFESSIONAL_PHOTO\"\n        }\n    ]\n}",
											"options": {
												"raw": {
													"language": "json"
												}
											}
										},
										"url": {
											"raw": "{{API_GATEWAY_URL}}/document/upload",
											"host": [
												"{{API_GATEWAY_URL}}"
											],
											"path": [
												"document",
												"upload"
											]
										}
									},
									"response": []
								},
								{
									"name": "Failure: Not Allowed parameter value (documentCategory)",
									"request": {
										"method": "POST",
										"header": [],
										"body": {
											"mode": "raw",
											"raw": "{\n    \"initiatorsystemcode\": \"ABC_WEB_APP\",\n    \"requestorid\": \"PROVIDER_COGNITO_ID_2\",\n    \"files\": [\n        {\n            \"documentownerid\": \"PROVIDER_COGNITO_ID_2\",\n            \"documentformat\": \"PNG\",\n            \"documentsize\": 1048576,\n            \"documentcategory\": \"TBD\"\n        }\n    ]\n}",
											"options": {
												"raw": {
													"language": "json"
												}
											}
										},
										"url": {
											"raw": "{{API_GATEWAY_URL}}/document/upload",
											"host": [
												"{{API_GATEWAY_URL}}"
											],
											"path": [
												"document",
												"upload"
											]
										}
									},
									"response": []
								},
								{
									"name": "Failure: Not Allowed parameter value (documentSize > 5MB = 5242880 Bytes)",
									"request": {
										"method": "POST",
										"header": [],
										"body": {
											"mode": "raw",
											"raw": "{\n    \"initiatorsystemcode\": \"ABC_WEB_APP\",\n    \"requestorid\": \"PROVIDER_COGNITO_ID_2\",\n    \"files\": [\n        {\n            \"documentownerid\": \"PROVIDER_COGNITO_ID_2\",\n            \"documentformat\": \"PNG\",\n            \"documentsize\": 1048576000,\n            \"documentcategory\": \"PROFESSIONAL_PHOTO\"\n        }\n    ]\n}",
											"options": {
												"raw": {
													"language": "json"
												}
											}
										},
										"url": {
											"raw": "{{API_GATEWAY_URL}}/document/upload",
											"host": [
												"{{API_GATEWAY_URL}}"
											],
											"path": [
												"document",
												"upload"
											]
										}
									},
									"response": []
								}
							]
						}
					]
				},
				{
					"name": "Get Documents List (by Status)",
					"item": [
						{
							"name": "Success scenarios",
							"item": [
								{
									"name": "Get all documents for all providers with specified status",
									"request": {
										"method": "POST",
										"header": [],
										"body": {
											"mode": "raw",
											"raw": "{\n    \"initiatorsystemcode\": \"ABC_WEB_APP\",\n    \"requestorid\": \"REQUESTOR_COGNITO_ID\",\n    \"documenttype\": \"providers\",\n    \"documentstatus\": \"Pending Review\",\n    \"documentownerid\": \"*\"\n}\n",
											"options": {
												"raw": {
													"language": "json"
												}
											}
										},
										"url": {
											"raw": "{{API_GATEWAY_URL}}/document/get-list-by-status",
											"host": [
												"{{API_GATEWAY_URL}}"
											],
											"path": [
												"document",
												"get-list-by-status"
											]
										}
									},
									"response": []
								},
								{
									"name": "Get all documents of the specific provider with specified status",
									"request": {
										"method": "POST",
										"header": [],
										"body": {
											"mode": "raw",
											"raw": "{\n    \"initiatorsystemcode\": \"ABC_WEB_APP\",\n    \"requestorid\": \"REQUESTOR_COGNITO_ID\",\n    \"documenttype\": \"providers\",\n    \"documentstatus\": \"Pending Review\",\n    \"documentownerid\": \"PROVIDER_COGNITO_ID_2\"\n}\n",
											"options": {
												"raw": {
													"language": "json"
												}
											}
										},
										"url": {
											"raw": "{{API_GATEWAY_URL}}/document/get-list-by-status",
											"host": [
												"{{API_GATEWAY_URL}}"
											],
											"path": [
												"document",
												"get-list-by-status"
											]
										}
									},
									"response": []
								}
							]
						},
						{
							"name": "Failure scenarios",
							"item": [
								{
									"name": "Failure: Missed required attribute (initiatorSystemCode)",
									"request": {
										"method": "POST",
										"header": [],
										"body": {
											"mode": "raw",
											"raw": "{\n    \"requestorid\": \"REQUESTOR_COGNITO_ID\",\n    \"documenttype\": \"providers\",\n    \"documentstatus\": \"Pending Review\",\n    \"documentownerid\": \"PROVIDER_COGNITO_ID_2\"\n}\n",
											"options": {
												"raw": {
													"language": "json"
												}
											}
										},
										"url": {
											"raw": "{{API_GATEWAY_URL}}/document/get-list-by-status",
											"host": [
												"{{API_GATEWAY_URL}}"
											],
											"path": [
												"document",
												"get-list-by-status"
											]
										}
									},
									"response": []
								},
								{
									"name": "Failure: Missed required attribute (requestorId)",
									"request": {
										"method": "POST",
										"header": [],
										"body": {
											"mode": "raw",
											"raw": "{\n    \"initiatorsystemcode\": \"ABC_WEB_APP\",\n    \"documenttype\": \"providers\",\n    \"documentstatus\": \"Pending Review\",\n    \"documentownerid\": \"PROVIDER_COGNITO_ID_2\"\n}\n",
											"options": {
												"raw": {
													"language": "json"
												}
											}
										},
										"url": {
											"raw": "{{API_GATEWAY_URL}}/document/get-list-by-status",
											"host": [
												"{{API_GATEWAY_URL}}"
											],
											"path": [
												"document",
												"get-list-by-status"
											]
										}
									},
									"response": []
								},
								{
									"name": "Failure: Missed required attribute (documentType)",
									"request": {
										"method": "POST",
										"header": [],
										"body": {
											"mode": "raw",
											"raw": "{\n    \"initiatorsystemcode\": \"ABC_WEB_APP\",\n    \"requestorid\": \"REQUESTOR_COGNITO_ID\",\n    \"documentstatus\": \"Pending Review\",\n    \"documentownerid\": \"PROVIDER_COGNITO_ID_2\"\n}\n",
											"options": {
												"raw": {
													"language": "json"
												}
											}
										},
										"url": {
											"raw": "{{API_GATEWAY_URL}}/document/get-list-by-status",
											"host": [
												"{{API_GATEWAY_URL}}"
											],
											"path": [
												"document",
												"get-list-by-status"
											]
										}
									},
									"response": []
								},
								{
									"name": "Failure: Missed required attribute (documentStatus)",
									"request": {
										"method": "POST",
										"header": [],
										"body": {
											"mode": "raw",
											"raw": "{\n    \"initiatorsystemcode\": \"ABC_WEB_APP\",\n    \"requestorid\": \"REQUESTOR_COGNITO_ID\",\n    \"documenttype\": \"providers\",\n    \"documentownerid\": \"PROVIDER_COGNITO_ID_2\"\n}\n",
											"options": {
												"raw": {
													"language": "json"
												}
											}
										},
										"url": {
											"raw": "{{API_GATEWAY_URL}}/document/get-list-by-status",
											"host": [
												"{{API_GATEWAY_URL}}"
											],
											"path": [
												"document",
												"get-list-by-status"
											]
										}
									},
									"response": []
								},
								{
									"name": "Failure: Missed required attribute (documentOwnerId)",
									"request": {
										"method": "POST",
										"header": [],
										"body": {
											"mode": "raw",
											"raw": "{\n    \"initiatorsystemcode\": \"ABC_WEB_APP\",\n    \"requestorid\": \"REQUESTOR_COGNITO_ID\",\n    \"documenttype\": \"providers\",\n    \"documentstatus\": \"Pending Review\"\n}\n",
											"options": {
												"raw": {
													"language": "json"
												}
											}
										},
										"url": {
											"raw": "{{API_GATEWAY_URL}}/document/get-list-by-status",
											"host": [
												"{{API_GATEWAY_URL}}"
											],
											"path": [
												"document",
												"get-list-by-status"
											]
										}
									},
									"response": []
								},
								{
									"name": "Failure: Unsupported value in the attribute (initiatorSystemCode)",
									"request": {
										"method": "POST",
										"header": [],
										"body": {
											"mode": "raw",
											"raw": "{\n    \"initiatorsystemcode\": \"TBD\",\n    \"requestorid\": \"REQUESTOR_COGNITO_ID\",\n    \"documenttype\": \"providers\",\n    \"documentstatus\": \"Pending Review\",\n    \"documentownerid\": \"PROVIDER_COGNITO_ID_2\"\n}\n",
											"options": {
												"raw": {
													"language": "json"
												}
											}
										},
										"url": {
											"raw": "{{API_GATEWAY_URL}}/document/get-list-by-status",
											"host": [
												"{{API_GATEWAY_URL}}"
											],
											"path": [
												"document",
												"get-list-by-status"
											]
										}
									},
									"response": []
								},
								{
									"name": "Failure: Unsupported value in the attribute (documentType)",
									"request": {
										"method": "POST",
										"header": [],
										"body": {
											"mode": "raw",
											"raw": "{\n    \"initiatorsystemcode\": \"ABC_WEB_APP\",\n    \"requestorid\": \"REQUESTOR_COGNITO_ID\",\n    \"documenttype\": \"TBD\",\n    \"documentstatus\": \"Pending Review\",\n    \"documentownerid\": \"PROVIDER_COGNITO_ID_2\"\n}\n",
											"options": {
												"raw": {
													"language": "json"
												}
											}
										},
										"url": {
											"raw": "{{API_GATEWAY_URL}}/document/get-list-by-status",
											"host": [
												"{{API_GATEWAY_URL}}"
											],
											"path": [
												"document",
												"get-list-by-status"
											]
										}
									},
									"response": []
								},
								{
									"name": "Failure: Unsupported value in the attribute (documentStatus)",
									"request": {
										"method": "POST",
										"header": [],
										"body": {
											"mode": "raw",
											"raw": "{\n    \"initiatorsystemcode\": \"ABC_WEB_APP\",\n    \"requestorid\": \"REQUESTOR_COGNITO_ID\",\n    \"documenttype\": \"providers\",\n    \"documentstatus\": \"TBD\",\n    \"documentownerid\": \"PROVIDER_COGNITO_ID_2\"\n}\n",
											"options": {
												"raw": {
													"language": "json"
												}
											}
										},
										"url": {
											"raw": "{{API_GATEWAY_URL}}/document/get-list-by-status",
											"host": [
												"{{API_GATEWAY_URL}}"
											],
											"path": [
												"document",
												"get-list-by-status"
											]
										}
									},
									"response": []
								}
							]
						}
					]
				},
				{
					"name": "Get Documents List (by Owner)",
					"item": [
						{
							"name": "Success scenarios",
							"item": [
								{
									"name": "Get all documents for specific user or organization (documentOwnerId)",
									"request": {
										"method": "POST",
										"header": [],
										"body": {
											"mode": "raw",
											"raw": "{\n    \"initiatorsystemcode\": \"ABC_WEB_APP\",\n    \"requestorid\": \"REQUESTOR_COGNITO_ID\",\n    \"documenttype\": \"providers\",\n    \"documentownerid\": \"PROVIDER_COGNITO_ID_1\"\n}",
											"options": {
												"raw": {
													"language": "json"
												}
											}
										},
										"url": {
											"raw": "{{API_GATEWAY_URL}}/document/get-list-by-owner",
											"host": [
												"{{API_GATEWAY_URL}}"
											],
											"path": [
												"document",
												"get-list-by-owner"
											]
										}
									},
									"response": []
								}
							]
						},
						{
							"name": "Failure scenarios",
							"item": [
								{
									"name": "Failure: Missed required attribute (initiatorSystemCode)",
									"request": {
										"method": "POST",
										"header": [],
										"body": {
											"mode": "raw",
											"raw": "{\n    \"requestorid\": \"REQUESTOR_COGNITO_ID\",\n    \"documenttype\": \"providers\",\n    \"documentownerid\": \"PROVIDER_COGNITO_ID_2\"\n}\n",
											"options": {
												"raw": {
													"language": "json"
												}
											}
										},
										"url": {
											"raw": "{{API_GATEWAY_URL}}/document/get-list-by-status",
											"host": [
												"{{API_GATEWAY_URL}}"
											],
											"path": [
												"document",
												"get-list-by-status"
											]
										}
									},
									"response": []
								},
								{
									"name": "Failure: Missed required attribute (requestorId)",
									"request": {
										"method": "POST",
										"header": [],
										"body": {
											"mode": "raw",
											"raw": "{\n    \"initiatorsystemcode\": \"ABC_WEB_APP\",\n    \"documenttype\": \"providers\",\n    \"documentownerid\": \"PROVIDER_COGNITO_ID_2\"\n}\n",
											"options": {
												"raw": {
													"language": "json"
												}
											}
										},
										"url": {
											"raw": "{{API_GATEWAY_URL}}/document/get-list-by-status",
											"host": [
												"{{API_GATEWAY_URL}}"
											],
											"path": [
												"document",
												"get-list-by-status"
											]
										}
									},
									"response": []
								},
								{
									"name": "Failure: Missed required attribute (documentType)",
									"request": {
										"method": "POST",
										"header": [],
										"body": {
											"mode": "raw",
											"raw": "{\n    \"initiatorsystemcode\": \"ABC_WEB_APP\",\n    \"requestorid\": \"REQUESTOR_COGNITO_ID\",\n    \"documentownerid\": \"PROVIDER_COGNITO_ID_2\"\n}\n",
											"options": {
												"raw": {
													"language": "json"
												}
											}
										},
										"url": {
											"raw": "{{API_GATEWAY_URL}}/document/get-list-by-status",
											"host": [
												"{{API_GATEWAY_URL}}"
											],
											"path": [
												"document",
												"get-list-by-status"
											]
										}
									},
									"response": []
								},
								{
									"name": "Failure: Missed required attribute (documentOwnerId)",
									"request": {
										"method": "POST",
										"header": [],
										"body": {
											"mode": "raw",
											"raw": "{\n    \"initiatorsystemcode\": \"ABC_WEB_APP\",\n    \"requestorid\": \"REQUESTOR_COGNITO_ID\",\n    \"documenttype\": \"providers\"\n}\n",
											"options": {
												"raw": {
													"language": "json"
												}
											}
										},
										"url": {
											"raw": "{{API_GATEWAY_URL}}/document/get-list-by-status",
											"host": [
												"{{API_GATEWAY_URL}}"
											],
											"path": [
												"document",
												"get-list-by-status"
											]
										}
									},
									"response": []
								},
								{
									"name": "Failure: Unsupported value in the attribute (initiatorSystemCode)",
									"request": {
										"method": "POST",
										"header": [],
										"body": {
											"mode": "raw",
											"raw": "{\n    \"initiatorsystemcode\": \"TBD\",\n    \"requestorid\": \"REQUESTOR_COGNITO_ID\",\n    \"documenttype\": \"providers\",\n    \"documentownerid\": \"PROVIDER_COGNITO_ID_2\"\n}\n",
											"options": {
												"raw": {
													"language": "json"
												}
											}
										},
										"url": {
											"raw": "{{API_GATEWAY_URL}}/document/get-list-by-status",
											"host": [
												"{{API_GATEWAY_URL}}"
											],
											"path": [
												"document",
												"get-list-by-status"
											]
										}
									},
									"response": []
								},
								{
									"name": "Failure: Unsupported value in the attribute (documentType)",
									"request": {
										"method": "POST",
										"header": [],
										"body": {
											"mode": "raw",
											"raw": "{\n    \"initiatorsystemcode\": \"ABC_WEB_APP\",\n    \"requestorid\": \"REQUESTOR_COGNITO_ID\",\n    \"documenttype\": \"TBD\",\n    \"documentownerid\": \"PROVIDER_COGNITO_ID_2\"\n}\n",
											"options": {
												"raw": {
													"language": "json"
												}
											}
										},
										"url": {
											"raw": "{{API_GATEWAY_URL}}/document/get-list-by-status",
											"host": [
												"{{API_GATEWAY_URL}}"
											],
											"path": [
												"document",
												"get-list-by-status"
											]
										}
									},
									"response": []
								}
							]
						}
					]
				},
				{
					"name": "Get Full Document Details (Metadata and URL)",
					"item": [
						{
							"name": "Success scenarios",
							"item": [
								{
									"name": "Get document's details by ID (including PreSigned URL) Copy",
									"request": {
										"method": "POST",
										"header": [],
										"body": {
											"mode": "raw",
											"raw": "{\n    \"initiatorsystemcode\": \"ABC_WEB_APP\",\n    \"requestorid\": \"REQUESTOR_COGNITO_ID\",\n    \"requestorip\": \"192.168.1.1\",\n    \"documenttype\": \"providers\",\n    \"documentid\": \"providers/uploaded/PROVIDER_COGNITO_ID_3/personal/PROFESSIONAL_PHOTO.PNG\"\n}",
											"options": {
												"raw": {
													"language": "json"
												}
											}
										},
										"url": {
											"raw": "{{API_GATEWAY_URL}}/document/get-document",
											"host": [
												"{{API_GATEWAY_URL}}"
											],
											"path": [
												"document",
												"get-document"
											]
										}
									},
									"response": []
								}
							]
						},
						{
							"name": "Failure scenarios",
							"item": [
								{
									"name": "Failure: Missed required parameter (initiatorsystemcode)",
									"request": {
										"method": "POST",
										"header": [],
										"body": {
											"mode": "raw",
											"raw": "{\n    \"requestorid\": \"REQUESTOR_COGNITO_ID\",\n    \"requestorip\": \"192.168.1.1\",\n    \"documenttype\": \"providers\",\n    \"documentid\": \"providers/uploaded/PROVIDER_COGNITO_ID_3/personal/PROFESSIONAL_PHOTO.PNG\"\n}",
											"options": {
												"raw": {
													"language": "json"
												}
											}
										},
										"url": {
											"raw": "{{API_GATEWAY_URL}}/document/get-document",
											"host": [
												"{{API_GATEWAY_URL}}"
											],
											"path": [
												"document",
												"get-document"
											]
										}
									},
									"response": []
								},
								{
									"name": "Failure: Missed required parameter (requestorid)",
									"request": {
										"method": "POST",
										"header": [],
										"body": {
											"mode": "raw",
											"raw": "{\n    \"initiatorsystemcode\": \"ABC_WEB_APP\",\n    \"requestorip\": \"192.168.1.1\",\n    \"documenttype\": \"providers\",\n    \"documentid\": \"providers/uploaded/PROVIDER_COGNITO_ID_3/personal/PROFESSIONAL_PHOTO.PNG\"\n}",
											"options": {
												"raw": {
													"language": "json"
												}
											}
										},
										"url": {
											"raw": "{{API_GATEWAY_URL}}/document/get-document",
											"host": [
												"{{API_GATEWAY_URL}}"
											],
											"path": [
												"document",
												"get-document"
											]
										}
									},
									"response": []
								},
								{
									"name": "Failure: Missed required parameter (requestorip)",
									"request": {
										"method": "POST",
										"header": [],
										"body": {
											"mode": "raw",
											"raw": "{\n    \"initiatorsystemcode\": \"ABC_WEB_APP\",\n    \"requestorid\": \"REQUESTOR_COGNITO_ID\",\n    \"documenttype\": \"providers\",\n    \"documentid\": \"providers/uploaded/PROVIDER_COGNITO_ID_3/personal/PROFESSIONAL_PHOTO.PNG\"\n}",
											"options": {
												"raw": {
													"language": "json"
												}
											}
										},
										"url": {
											"raw": "{{API_GATEWAY_URL}}/document/get-document",
											"host": [
												"{{API_GATEWAY_URL}}"
											],
											"path": [
												"document",
												"get-document"
											]
										}
									},
									"response": []
								},
								{
									"name": "Failure: Missed required parameter (documenttype)",
									"request": {
										"method": "POST",
										"header": [],
										"body": {
											"mode": "raw",
											"raw": "{\n    \"initiatorsystemcode\": \"ABC_WEB_APP\",\n    \"requestorid\": \"REQUESTOR_COGNITO_ID\",\n    \"requestorip\": \"192.168.1.1\",\n    \"documentid\": \"providers/uploaded/PROVIDER_COGNITO_ID_3/personal/PROFESSIONAL_PHOTO.PNG\"\n}",
											"options": {
												"raw": {
													"language": "json"
												}
											}
										},
										"url": {
											"raw": "{{API_GATEWAY_URL}}/document/get-document",
											"host": [
												"{{API_GATEWAY_URL}}"
											],
											"path": [
												"document",
												"get-document"
											]
										}
									},
									"response": []
								},
								{
									"name": "Failure: Missed required parameter (documentid)",
									"request": {
										"method": "POST",
										"header": [],
										"body": {
											"mode": "raw",
											"raw": "{\n    \"initiatorsystemcode\": \"ABC_WEB_APP\",\n    \"requestorid\": \"REQUESTOR_COGNITO_ID\",\n    \"requestorip\": \"192.168.1.1\",\n    \"documenttype\": \"providers\"\n}",
											"options": {
												"raw": {
													"language": "json"
												}
											}
										},
										"url": {
											"raw": "{{API_GATEWAY_URL}}/document/get-document",
											"host": [
												"{{API_GATEWAY_URL}}"
											],
											"path": [
												"document",
												"get-document"
											]
										}
									},
									"response": []
								},
								{
									"name": "Failure: Unsupported parameter value (initiatorsystemcode)",
									"request": {
										"method": "POST",
										"header": [],
										"body": {
											"mode": "raw",
											"raw": "{\n    \"initiatorsystemcode\": \"TBD\",\n    \"requestorid\": \"REQUESTOR_COGNITO_ID\",\n    \"requestorip\": \"192.168.1.1\",\n    \"documenttype\": \"providers\",\n    \"documentid\": \"providers/uploaded/PROVIDER_COGNITO_ID_3/personal/PROFESSIONAL_PHOTO.PNG\"\n}",
											"options": {
												"raw": {
													"language": "json"
												}
											}
										},
										"url": {
											"raw": "{{API_GATEWAY_URL}}/document/get-document",
											"host": [
												"{{API_GATEWAY_URL}}"
											],
											"path": [
												"document",
												"get-document"
											]
										}
									},
									"response": []
								},
								{
									"name": "Failure: Unsupported parameter value (requestorip)",
									"request": {
										"method": "POST",
										"header": [],
										"body": {
											"mode": "raw",
											"raw": "{\n    \"initiatorsystemcode\": \"ABC_WEB_APP\",\n    \"requestorid\": \"REQUESTOR_COGNITO_ID\",\n    \"requestorip\": \"TBD\",\n    \"documenttype\": \"providers\",\n    \"documentid\": \"providers/uploaded/PROVIDER_COGNITO_ID_3/personal/PROFESSIONAL_PHOTO.PNG\"\n}",
											"options": {
												"raw": {
													"language": "json"
												}
											}
										},
										"url": {
											"raw": "{{API_GATEWAY_URL}}/document/get-document",
											"host": [
												"{{API_GATEWAY_URL}}"
											],
											"path": [
												"document",
												"get-document"
											]
										}
									},
									"response": []
								},
								{
									"name": "Failure: Unsupported parameter value (documenttype)",
									"request": {
										"method": "POST",
										"header": [],
										"body": {
											"mode": "raw",
											"raw": "{\n    \"initiatorsystemcode\": \"ABC_WEB_APP\",\n    \"requestorid\": \"REQUESTOR_COGNITO_ID\",\n    \"requestorip\": \"192.168.1.1\",\n    \"documenttype\": \"TBD\",\n    \"documentid\": \"providers/uploaded/PROVIDER_COGNITO_ID_3/personal/PROFESSIONAL_PHOTO.PNG\"\n}",
											"options": {
												"raw": {
													"language": "json"
												}
											}
										},
										"url": {
											"raw": "{{API_GATEWAY_URL}}/document/get-document",
											"host": [
												"{{API_GATEWAY_URL}}"
											],
											"path": [
												"document",
												"get-document"
											]
										}
									},
									"response": []
								}
							]
						}
					]
				},
				{
					"name": "Get Document URL",
					"item": [
						{
							"name": "Success scenarios",
							"item": [
								{
									"name": "Get document's url by ID (PreSigned URL)",
									"request": {
										"method": "POST",
										"header": [],
										"body": {
											"mode": "raw",
											"raw": "{\n    \"initiatorsystemcode\": \"ABC_WEB_APP\",\n    \"requestorid\": \"REQUESTOR_COGNITO_ID\",\n    \"requestorip\": \"192.168.1.1\",\n    \"documenttype\": \"providers\",\n    \"documentid\": \"providers/uploaded/PROVIDER_COGNITO_ID_3/personal/PROFESSIONAL_PHOTO.PNG\"\n}",
											"options": {
												"raw": {
													"language": "json"
												}
											}
										},
										"url": {
											"raw": "{{API_GATEWAY_URL}}/document/get-url",
											"host": [
												"{{API_GATEWAY_URL}}"
											],
											"path": [
												"document",
												"get-url"
											]
										}
									},
									"response": []
								}
							]
						},
						{
							"name": "Failure scenarios",
							"item": [
								{
									"name": "Failure: Missed required parameter (initiatorsystemcode)",
									"request": {
										"method": "POST",
										"header": [],
										"body": {
											"mode": "raw",
											"raw": "{\n    \"requestorid\": \"REQUESTOR_COGNITO_ID\",\n    \"requestorip\": \"192.168.1.1\",\n    \"documenttype\": \"providers\",\n    \"documentid\": \"providers/uploaded/PROVIDER_COGNITO_ID_3/personal/PROFESSIONAL_PHOTO.PNG\"\n}",
											"options": {
												"raw": {
													"language": "json"
												}
											}
										},
										"url": {
											"raw": "{{API_GATEWAY_URL}}/document/get-url",
											"host": [
												"{{API_GATEWAY_URL}}"
											],
											"path": [
												"document",
												"get-url"
											]
										}
									},
									"response": []
								},
								{
									"name": "Failure: Missed required parameter (requestorid)",
									"request": {
										"method": "POST",
										"header": [],
										"body": {
											"mode": "raw",
											"raw": "{\n    \"initiatorsystemcode\": \"ABC_WEB_APP\",\n    \"requestorip\": \"192.168.1.1\",\n    \"documenttype\": \"providers\",\n    \"documentid\": \"providers/uploaded/PROVIDER_COGNITO_ID_3/personal/PROFESSIONAL_PHOTO.PNG\"\n}",
											"options": {
												"raw": {
													"language": "json"
												}
											}
										},
										"url": {
											"raw": "{{API_GATEWAY_URL}}/document/get-url",
											"host": [
												"{{API_GATEWAY_URL}}"
											],
											"path": [
												"document",
												"get-url"
											]
										}
									},
									"response": []
								},
								{
									"name": "Failure: Missed required parameter (requestorip)",
									"request": {
										"method": "POST",
										"header": [],
										"body": {
											"mode": "raw",
											"raw": "{\n    \"initiatorsystemcode\": \"ABC_WEB_APP\",\n    \"requestorid\": \"REQUESTOR_COGNITO_ID\",\n    \"documenttype\": \"providers\",\n    \"documentid\": \"providers/uploaded/PROVIDER_COGNITO_ID_3/personal/PROFESSIONAL_PHOTO.PNG\"\n}",
											"options": {
												"raw": {
													"language": "json"
												}
											}
										},
										"url": {
											"raw": "{{API_GATEWAY_URL}}/document/get-url",
											"host": [
												"{{API_GATEWAY_URL}}"
											],
											"path": [
												"document",
												"get-url"
											]
										}
									},
									"response": []
								},
								{
									"name": "Failure: Missed required parameter (documenttype)",
									"request": {
										"method": "POST",
										"header": [],
										"body": {
											"mode": "raw",
											"raw": "{\n    \"initiatorsystemcode\": \"ABC_WEB_APP\",\n    \"requestorid\": \"REQUESTOR_COGNITO_ID\",\n    \"requestorip\": \"192.168.1.1\",\n    \"documentid\": \"providers/uploaded/PROVIDER_COGNITO_ID_3/personal/PROFESSIONAL_PHOTO.PNG\"\n}",
											"options": {
												"raw": {
													"language": "json"
												}
											}
										},
										"url": {
											"raw": "{{API_GATEWAY_URL}}/document/get-url",
											"host": [
												"{{API_GATEWAY_URL}}"
											],
											"path": [
												"document",
												"get-url"
											]
										}
									},
									"response": []
								},
								{
									"name": "Failure: Missed required parameter (documentid)",
									"request": {
										"method": "POST",
										"header": [],
										"body": {
											"mode": "raw",
											"raw": "{\n    \"initiatorsystemcode\": \"ABC_WEB_APP\",\n    \"requestorid\": \"REQUESTOR_COGNITO_ID\",\n    \"requestorip\": \"192.168.1.1\",\n    \"documenttype\": \"providers\"\n}",
											"options": {
												"raw": {
													"language": "json"
												}
											}
										},
										"url": {
											"raw": "{{API_GATEWAY_URL}}/document/get-url",
											"host": [
												"{{API_GATEWAY_URL}}"
											],
											"path": [
												"document",
												"get-url"
											]
										}
									},
									"response": []
								},
								{
									"name": "Failure: Unsupported parameter value (initiatorsystemcode)",
									"request": {
										"method": "POST",
										"header": [],
										"body": {
											"mode": "raw",
											"raw": "{\n    \"initiatorsystemcode\": \"TBD\",\n    \"requestorid\": \"REQUESTOR_COGNITO_ID\",\n    \"requestorip\": \"192.168.1.1\",\n    \"documenttype\": \"providers\",\n    \"documentid\": \"providers/uploaded/PROVIDER_COGNITO_ID_3/personal/PROFESSIONAL_PHOTO.PNG\"\n}",
											"options": {
												"raw": {
													"language": "json"
												}
											}
										},
										"url": {
											"raw": "{{API_GATEWAY_URL}}/document/get-url",
											"host": [
												"{{API_GATEWAY_URL}}"
											],
											"path": [
												"document",
												"get-url"
											]
										}
									},
									"response": []
								},
								{
									"name": "Failure: Unsupported parameter value (requestorip)",
									"request": {
										"method": "POST",
										"header": [],
										"body": {
											"mode": "raw",
											"raw": "{\n    \"initiatorsystemcode\": \"ABC_WEB_APP\",\n    \"requestorid\": \"REQUESTOR_COGNITO_ID\",\n    \"requestorip\": \"TBD\",\n    \"documenttype\": \"providers\",\n    \"documentid\": \"providers/uploaded/PROVIDER_COGNITO_ID_3/personal/PROFESSIONAL_PHOTO.PNG\"\n}",
											"options": {
												"raw": {
													"language": "json"
												}
											}
										},
										"url": {
											"raw": "{{API_GATEWAY_URL}}/document/get-url",
											"host": [
												"{{API_GATEWAY_URL}}"
											],
											"path": [
												"document",
												"get-url"
											]
										}
									},
									"response": []
								},
								{
									"name": "Failure: Unsupported parameter value (documenttype)",
									"request": {
										"method": "POST",
										"header": [],
										"body": {
											"mode": "raw",
											"raw": "{\n    \"initiatorsystemcode\": \"ABC_WEB_APP\",\n    \"requestorid\": \"REQUESTOR_COGNITO_ID\",\n    \"requestorip\": \"192.168.1.1\",\n    \"documenttype\": \"TBD\",\n    \"documentid\": \"providers/uploaded/PROVIDER_COGNITO_ID_3/personal/PROFESSIONAL_PHOTO.PNG\"\n}",
											"options": {
												"raw": {
													"language": "json"
												}
											}
										},
										"url": {
											"raw": "{{API_GATEWAY_URL}}/document/get-url",
											"host": [
												"{{API_GATEWAY_URL}}"
											],
											"path": [
												"document",
												"get-url"
											]
										}
									},
									"response": []
								}
							]
						}
					]
				},
				{
					"name": "Get Document Metadata",
					"item": [
						{
							"name": "Success scenarios",
							"item": [
								{
									"name": "Get document's metadata by ID",
									"request": {
										"method": "POST",
										"header": [],
										"body": {
											"mode": "raw",
											"raw": "{\n    \"initiatorsystemcode\": \"ABC_WEB_APP\",\n    \"requestorid\": \"REQUESTOR_COGNITO_ID\",\n    \"requestorip\": \"192.168.1.1\",\n   \"documenttype\": \"insurance\",\n    \"documentid\": \"insurance/uploaded/PROVIDER_COGNITO_ID_1/claims/CLAIM_00012345678.PDF\"\n}",
											"options": {
												"raw": {
													"language": "json"
												}
											}
										},
										"url": {
											"raw": "{{API_GATEWAY_URL}}/document/get-metadata",
											"host": [
												"{{API_GATEWAY_URL}}"
											],
											"path": [
												"document",
												"get-metadata"
											]
										}
									},
									"response": []
								}
							]
						},
						{
							"name": "Failure scenarios",
							"item": [
								{
									"name": "Failure: Missed required parameter (initiatorsystemcode)",
									"request": {
										"method": "POST",
										"header": [],
										"body": {
											"mode": "raw",
											"raw": "{\n    \"requestorid\": \"REQUESTOR_COGNITO_ID\",\n    \"requestorip\": \"192.168.1.1\",\n    \"documenttype\": \"insurance\",\n    \"documentid\": \"insurance/uploaded/PROVIDER_COGNITO_ID_1/claims/CLAIM_00012345678.PDF\"\n}",
											"options": {
												"raw": {
													"language": "json"
												}
											}
										},
										"url": {
											"raw": "{{API_GATEWAY_URL}}/document/get-metadata",
											"host": [
												"{{API_GATEWAY_URL}}"
											],
											"path": [
												"document",
												"get-metadata"
											]
										}
									},
									"response": []
								},
								{
									"name": "Failure: Missed required parameter (requestorid)",
									"request": {
										"method": "POST",
										"header": [],
										"body": {
											"mode": "raw",
											"raw": "{\n    \"initiatorsystemcode\": \"ABC_WEB_APP\",\n    \"requestorip\": \"192.168.1.1\",\n    \"documenttype\": \"insurance\",\n    \"documentid\": \"insurance/uploaded/PROVIDER_COGNITO_ID_1/claims/CLAIM_00012345678.PDF\"\n}",
											"options": {
												"raw": {
													"language": "json"
												}
											}
										},
										"url": {
											"raw": "{{API_GATEWAY_URL}}/document/get-metadata",
											"host": [
												"{{API_GATEWAY_URL}}"
											],
											"path": [
												"document",
												"get-metadata"
											]
										}
									},
									"response": []
								},
								{
									"name": "Failure: Missed required parameter (requestorip)",
									"request": {
										"method": "POST",
										"header": [],
										"body": {
											"mode": "raw",
											"raw": "{\n    \"initiatorsystemcode\": \"ABC_WEB_APP\",\n    \"requestorid\": \"REQUESTOR_COGNITO_ID\",\n    \"documenttype\": \"insurance\",\n    \"documentid\": \"insurance/uploaded/PROVIDER_COGNITO_ID_1/claims/CLAIM_00012345678.PDF\"\n}",
											"options": {
												"raw": {
													"language": "json"
												}
											}
										},
										"url": {
											"raw": "{{API_GATEWAY_URL}}/document/get-metadata",
											"host": [
												"{{API_GATEWAY_URL}}"
											],
											"path": [
												"document",
												"get-metadata"
											]
										}
									},
									"response": []
								},
								{
									"name": "Failure: Missed required parameter (documenttype)",
									"request": {
										"method": "POST",
										"header": [],
										"body": {
											"mode": "raw",
											"raw": "{\n    \"initiatorsystemcode\": \"ABC_WEB_APP\",\n    \"requestorid\": \"REQUESTOR_COGNITO_ID\",\n    \"requestorip\": \"192.168.1.1\",\n    \"documentid\": \"insurance/uploaded/PROVIDER_COGNITO_ID_1/claims/CLAIM_00012345678.PDF\"\n}",
											"options": {
												"raw": {
													"language": "json"
												}
											}
										},
										"url": {
											"raw": "{{API_GATEWAY_URL}}/document/get-metadata",
											"host": [
												"{{API_GATEWAY_URL}}"
											],
											"path": [
												"document",
												"get-metadata"
											]
										}
									},
									"response": []
								},
								{
									"name": "Failure: Missed required parameter (documentid)",
									"request": {
										"method": "POST",
										"header": [],
										"body": {
											"mode": "raw",
											"raw": "{\n    \"initiatorsystemcode\": \"ABC_WEB_APP\",\n    \"requestorid\": \"REQUESTOR_COGNITO_ID\",\n    \"requestorip\": \"192.168.1.1\",\n    \"documenttype\": \"insurance\"\n}",
											"options": {
												"raw": {
													"language": "json"
												}
											}
										},
										"url": {
											"raw": "{{API_GATEWAY_URL}}/document/get-metadata",
											"host": [
												"{{API_GATEWAY_URL}}"
											],
											"path": [
												"document",
												"get-metadata"
											]
										}
									},
									"response": []
								},
								{
									"name": "Failure: Unsupported parameter value (initiatorsystemcode)",
									"request": {
										"method": "POST",
										"header": [],
										"body": {
											"mode": "raw",
											"raw": "{\n    \"initiatorsystemcode\": \"TBD\",\n    \"requestorid\": \"REQUESTOR_COGNITO_ID\",\n    \"requestorip\": \"192.168.1.1\",\n    \"documenttype\": \"insurance\",\n    \"documentid\": \"insurance/uploaded/PROVIDER_COGNITO_ID_1/claims/CLAIM_00012345678.PDF\"\n}",
											"options": {
												"raw": {
													"language": "json"
												}
											}
										},
										"url": {
											"raw": "{{API_GATEWAY_URL}}/document/get-metadata",
											"host": [
												"{{API_GATEWAY_URL}}"
											],
											"path": [
												"document",
												"get-metadata"
											]
										}
									},
									"response": []
								},
								{
									"name": "Failure: Unsupported parameter value (requestorip)",
									"request": {
										"method": "POST",
										"header": [],
										"body": {
											"mode": "raw",
											"raw": "{\n    \"initiatorsystemcode\": \"ABC_WEB_APP\",\n    \"requestorid\": \"REQUESTOR_COGNITO_ID\",\n    \"requestorip\": \"TBD\",\n    \"documenttype\": \"insurance\",\n    \"documentid\": \"insurance/uploaded/PROVIDER_COGNITO_ID_1/claims/CLAIM_00012345678.PDF\"\n}",
											"options": {
												"raw": {
													"language": "json"
												}
											}
										},
										"url": {
											"raw": "{{API_GATEWAY_URL}}/document/get-metadata",
											"host": [
												"{{API_GATEWAY_URL}}"
											],
											"path": [
												"document",
												"get-metadata"
											]
										}
									},
									"response": []
								},
								{
									"name": "Failure: Unsupported parameter value (documenttype)",
									"request": {
										"method": "POST",
										"header": [],
										"body": {
											"mode": "raw",
											"raw": "{\n    \"initiatorsystemcode\": \"ABC_WEB_APP\",\n    \"requestorid\": \"REQUESTOR_COGNITO_ID\",\n    \"requestorip\": \"192.168.1.1\",\n    \"documenttype\": \"TBD\",\n    \"documentid\": \"insurance/uploaded/PROVIDER_COGNITO_ID_1/claims/CLAIM_00012345678.PDF\"\n}",
											"options": {
												"raw": {
													"language": "json"
												}
											}
										},
										"url": {
											"raw": "{{API_GATEWAY_URL}}/document/get-metadata",
											"host": [
												"{{API_GATEWAY_URL}}"
											],
											"path": [
												"document",
												"get-metadata"
											]
										}
									},
									"response": []
								}
							]
						}
					]
				}
			]
		},
		{
			"name": "Verification",
			"item": [
				{
					"name": "Failure scenarios",
					"item": [
						{
							"name": "Failure: Missed required attribute (initiatorsystemcode)",
							"request": {
								"method": "POST",
								"header": [],
								"body": {
									"mode": "raw",
									"raw": "{\n    \"requestorid\": \"REQUESTOR_COGNITO_ID\",\n    \"requestorip\": \"192.168.1.1\",\n    \"documenttype\": \"insurance\",\n    \"documentid\": \"insurance/uploaded/PROVIDER_COGNITO_ID_1/claims/CLAIM_00012345678.PDF\",\n    \"verificationstatus\": \"Under Review\",\n    \"comment\": \"Started process\"\n}",
									"options": {
										"raw": {
											"language": "json"
										}
									}
								},
								"url": {
									"raw": "{{API_GATEWAY_URL}}/verify/update-trail",
									"host": [
										"{{API_GATEWAY_URL}}"
									],
									"path": [
										"verify",
										"update-trail"
									]
								}
							},
							"response": []
						},
						{
							"name": "Failure: Missed required attribute (requestorid)",
							"request": {
								"method": "POST",
								"header": [],
								"body": {
									"mode": "raw",
									"raw": "{\n    \"initiatorsystemcode\": \"ABC_WEB_APP\",\n    \"requestorip\": \"192.168.1.1\",\n    \"documenttype\": \"insurance\",\n    \"documentid\": \"insurance/uploaded/PROVIDER_COGNITO_ID_1/claims/CLAIM_00012345678.PDF\",\n    \"verificationstatus\": \"Under Review\",\n    \"comment\": \"Started process\"\n}",
									"options": {
										"raw": {
											"language": "json"
										}
									}
								},
								"url": {
									"raw": "{{API_GATEWAY_URL}}/verify/update-trail",
									"host": [
										"{{API_GATEWAY_URL}}"
									],
									"path": [
										"verify",
										"update-trail"
									]
								}
							},
							"response": []
						},
						{
							"name": "Failure: Missed required attribute (requestorip)",
							"request": {
								"method": "POST",
								"header": [],
								"body": {
									"mode": "raw",
									"raw": "{\n    \"initiatorsystemcode\": \"ABC_WEB_APP\",\n    \"requestorid\": \"REQUESTOR_COGNITO_ID\",\n    \"documenttype\": \"insurance\",\n    \"documentid\": \"insurance/uploaded/PROVIDER_COGNITO_ID_1/claims/CLAIM_00012345678.PDF\",\n    \"verificationstatus\": \"Under Review\",\n    \"comment\": \"Started process\"\n}",
									"options": {
										"raw": {
											"language": "json"
										}
									}
								},
								"url": {
									"raw": "{{API_GATEWAY_URL}}/verify/update-trail",
									"host": [
										"{{API_GATEWAY_URL}}"
									],
									"path": [
										"verify",
										"update-trail"
									]
								}
							},
							"response": []
						},
						{
							"name": "Failure: Missed required attribute (documenttype)",
							"request": {
								"method": "POST",
								"header": [],
								"body": {
									"mode": "raw",
									"raw": "{\n    \"initiatorsystemcode\": \"ABC_WEB_APP\",\n    \"requestorip\": \"192.168.1.1\",\n    \"requestorid\": \"REQUESTOR_COGNITO_ID\",\n    \"documentid\": \"insurance/uploaded/PROVIDER_COGNITO_ID_1/claims/CLAIM_00012345678.PDF\",\n    \"verificationstatus\": \"Under Review\",\n    \"comment\": \"Started process\"\n}",
									"options": {
										"raw": {
											"language": "json"
										}
									}
								},
								"url": {
									"raw": "{{API_GATEWAY_URL}}/verify/update-trail",
									"host": [
										"{{API_GATEWAY_URL}}"
									],
									"path": [
										"verify",
										"update-trail"
									]
								}
							},
							"response": []
						},
						{
							"name": "Failure: Missed required attribute (documentid)",
							"request": {
								"method": "POST",
								"header": [],
								"body": {
									"mode": "raw",
									"raw": "{\n    \"initiatorsystemcode\": \"ABC_WEB_APP\",\n    \"requestorid\": \"REQUESTOR_COGNITO_ID\",\n    \"requestorip\": \"192.168.1.1\",\n    \"documenttype\": \"insurance\",\n    \"verificationstatus\": \"Under Review\",\n    \"comment\": \"Started process\"\n}",
									"options": {
										"raw": {
											"language": "json"
										}
									}
								},
								"url": {
									"raw": "{{API_GATEWAY_URL}}/verify/update-trail",
									"host": [
										"{{API_GATEWAY_URL}}"
									],
									"path": [
										"verify",
										"update-trail"
									]
								}
							},
							"response": []
						},
						{
							"name": "Failure: Missed required attribute (verificationStatus)",
							"request": {
								"method": "POST",
								"header": [],
								"body": {
									"mode": "raw",
									"raw": "{\n    \"initiatorsystemcode\": \"ABC_WEB_APP\",\n    \"requestorid\": \"REQUESTOR_COGNITO_ID\",\n    \"requestorip\": \"192.168.1.1\",\n    \"documenttype\": \"insurance\",\n    \"documentid\": \"insurance/uploaded/PROVIDER_COGNITO_ID_1/claims/CLAIM_00012345678.PDF\",\n    \"comment\": \"Started process\"\n}",
									"options": {
										"raw": {
											"language": "json"
										}
									}
								},
								"url": {
									"raw": "{{API_GATEWAY_URL}}/verify/update-trail",
									"host": [
										"{{API_GATEWAY_URL}}"
									],
									"path": [
										"verify",
										"update-trail"
									]
								}
							},
							"response": []
						},
						{
							"name": "Failure: Unsupported value in the attribute (initiatorsystemcode)",
							"request": {
								"method": "POST",
								"header": [],
								"body": {
									"mode": "raw",
									"raw": "{\n    \"initiatorsystemcode\": \"ABC_WEB_APP\",\n    \"requestorid\": \"REQUESTOR_COGNITO_ID\",\n    \"requestorip\": \"192.168.1.1\",\n    \"documenttype\": \"insurance\",\n    \"documentid\": \"insurance/uploaded/PROVIDER_COGNITO_ID_1/claims/CLAIM_00012345678.PDF\",\n    \"verificationstatus\": \"Under Review\",\n    \"comment\": \"Started process\"\n}",
									"options": {
										"raw": {
											"language": "json"
										}
									}
								},
								"url": {
									"raw": "{{API_GATEWAY_URL}}/verify/update-trail",
									"host": [
										"{{API_GATEWAY_URL}}"
									],
									"path": [
										"verify",
										"update-trail"
									]
								}
							},
							"response": []
						},
						{
							"name": "Failure: Unsupported value in the attribute (requestorip)",
							"request": {
								"method": "POST",
								"header": [],
								"body": {
									"mode": "raw",
									"raw": "{\n    \"initiatorsystemcode\": \"ABC_WEB_APP\",\n    \"requestorid\": \"REQUESTOR_COGNITO_ID\",\n    \"requestorip\": \"TBD\",\n    \"documenttype\": \"insurance\",\n    \"documentid\": \"insurance/uploaded/PROVIDER_COGNITO_ID_1/claims/CLAIM_00012345678.PDF\",\n    \"verificationstatus\": \"Under Review\",\n    \"comment\": \"Started process\"\n}",
									"options": {
										"raw": {
											"language": "json"
										}
									}
								},
								"url": {
									"raw": "{{API_GATEWAY_URL}}/verify/update-trail",
									"host": [
										"{{API_GATEWAY_URL}}"
									],
									"path": [
										"verify",
										"update-trail"
									]
								}
							},
							"response": []
						},
						{
							"name": "Failure: Unsupported value in the attribute (documenttyppe)",
							"request": {
								"method": "POST",
								"header": [],
								"body": {
									"mode": "raw",
									"raw": "{\n    \"initiatorsystemcode\": \"ABC_WEB_APP\",\n    \"requestorid\": \"REQUESTOR_COGNITO_ID\",\n    \"requestorip\": \"192.168.1.1\",\n    \"documenttype\": \"TBD\",\n    \"documentid\": \"insurance/uploaded/PROVIDER_COGNITO_ID_1/claims/CLAIM_00012345678.PDF\",\n    \"verificationstatus\": \"Under Review\",\n    \"comment\": \"Started process\"\n}",
									"options": {
										"raw": {
											"language": "json"
										}
									}
								},
								"url": {
									"raw": "{{API_GATEWAY_URL}}/verify/update-trail",
									"host": [
										"{{API_GATEWAY_URL}}"
									],
									"path": [
										"verify",
										"update-trail"
									]
								}
							},
							"response": []
						},
						{
							"name": "Failure: Unsupported value in the attribute (requestorip)",
							"request": {
								"method": "POST",
								"header": [],
								"body": {
									"mode": "raw",
									"raw": "{\n    \"initiatorsystemcode\": \"ABC_WEB_APP\",\n    \"requestorid\": \"REQUESTOR_COGNITO_ID\",\n    \"requestorip\": \"192.168.1.1\",\n    \"documenttype\": \"insurance\",\n    \"documentid\": \"insurance/uploaded/PROVIDER_COGNITO_ID_1/claims/CLAIM_00012345678.PDF\",\n    \"verificationstatus\": \"TBD\",\n    \"comment\": \"Started process\"\n}",
									"options": {
										"raw": {
											"language": "json"
										}
									}
								},
								"url": {
									"raw": "{{API_GATEWAY_URL}}/verify/update-trail",
									"host": [
										"{{API_GATEWAY_URL}}"
									],
									"path": [
										"verify",
										"update-trail"
									]
								}
							},
							"response": []
						},
						{
							"name": "Failure: Unsupported transition (to Rejected from non Under Review)",
							"request": {
								"method": "POST",
								"header": [],
								"body": {
									"mode": "raw",
									"raw": "{\n    \"initiatorsystemcode\": \"ABC_WEB_APP\",\n    \"requestorid\": \"REQUESTOR_COGNITO_ID\",\n    \"requestorip\": \"192.168.1.1\",\n    \"documenttype\": \"insurance\",\n    \"documentid\": \"insurance/uploaded/PROVIDER_COGNITO_ID_1/claims/CLAIM_00012345678.PDF\",\n    \"verificationstatus\": \"Rejected\",\n    \"comment\": \"Rejected. Document number does not match government values\"\n}",
									"options": {
										"raw": {
											"language": "json"
										}
									}
								},
								"url": {
									"raw": "{{API_GATEWAY_URL}}/verify/update-trail",
									"host": [
										"{{API_GATEWAY_URL}}"
									],
									"path": [
										"verify",
										"update-trail"
									]
								}
							},
							"response": []
						},
						{
							"name": "Failure: Unsupported transition (to Verified from non Under Review)",
							"request": {
								"method": "POST",
								"header": [],
								"body": {
									"mode": "raw",
									"raw": "{\n    \"initiatorsystemcode\": \"ABC_WEB_APP\",\n    \"requestorid\": \"REQUESTOR_COGNITO_ID\",\n    \"requestorip\": \"192.168.1.1\",\n    \"documenttype\": \"insurance\",\n    \"documentid\": \"insurance/uploaded/PROVIDER_COGNITO_ID_1/claims/CLAIM_00012345678.PDF\",\n    \"verificationstatus\": \"Verified\",\n    \"comment\": \"Document was reviewed. No issues found\"\n}",
									"options": {
										"raw": {
											"language": "json"
										}
									}
								},
								"url": {
									"raw": "{{API_GATEWAY_URL}}/verify/update-trail",
									"host": [
										"{{API_GATEWAY_URL}}"
									],
									"path": [
										"verify",
										"update-trail"
									]
								}
							},
							"response": []
						},
						{
							"name": "Failure: Unsupported transition (attempt to move to the same status)",
							"request": {
								"method": "POST",
								"header": [],
								"body": {
									"mode": "raw",
									"raw": "{\n    \"initiatorsystemcode\": \"ABC_WEB_APP\",\n    \"requestorid\": \"REQUESTOR_COGNITO_ID\",\n    \"requestorip\": \"192.168.1.1\",\n    \"documenttype\": \"insurance\",\n    \"documentid\": \"insurance/uploaded/PROVIDER_COGNITO_ID_1/claims/CLAIM_00012345678.PDF\",\n    \"verificationstatus\": \"Pending Review\",\n    \"comment\": \"Document was reviewed. No issues found\"\n}",
									"options": {
										"raw": {
											"language": "json"
										}
									}
								},
								"url": {
									"raw": "{{API_GATEWAY_URL}}/verify/update-trail",
									"host": [
										"{{API_GATEWAY_URL}}"
									],
									"path": [
										"verify",
										"update-trail"
									]
								}
							},
							"response": []
						}
					]
				},
				{
					"name": "Success scenarios",
					"item": [
						{
							"name": "Verify Document: Start Process",
							"request": {
								"method": "POST",
								"header": [],
								"body": {
									"mode": "raw",
									"raw": "{\n   \"initiatorsystemcode\": \"ABC_WEB_APP\",\n    \"requestorid\": \"REQUESTOR_COGNITO_ID\",\n    \"requestorip\": \"192.168.1.1\",\n    \"documenttype\": \"insurance\",\n    \"documentid\": \"insurance/uploaded/PROVIDER_COGNITO_ID_1/claims/CLAIM_00012345678.PDF\",\n    \"verificationstatus\": \"Under Review\",\n    \"comment\": \"\"\n}",
									"options": {
										"raw": {
											"language": "json"
										}
									}
								},
								"url": {
									"raw": "{{API_GATEWAY_URL}}/verify/update-trail",
									"host": [
										"{{API_GATEWAY_URL}}"
									],
									"path": [
										"verify",
										"update-trail"
									]
								}
							},
							"response": []
						},
						{
							"name": "Verify Document: Confirm as Valid",
							"request": {
								"method": "POST",
								"header": [],
								"body": {
									"mode": "raw",
									"raw": "{\n    \"initiatorsystemcode\": \"ABC_WEB_APP\",\n    \"requestorid\": \"REQUESTOR_COGNITO_ID\",\n    \"requestorip\": \"192.168.1.1\",\n    \"documenttype\": \"insurance\",\n    \"documentid\": \"insurance/uploaded/PROVIDER_COGNITO_ID_1/claims/CLAIM_00012345678.PDF\",\n    \"verificationstatus\": \"Verified\",\n    \"comment\": \"Verified. No issues found\"\n}",
									"options": {
										"raw": {
											"language": "json"
										}
									}
								},
								"url": {
									"raw": "{{API_GATEWAY_URL}}/verify/update-trail",
									"host": [
										"{{API_GATEWAY_URL}}"
									],
									"path": [
										"verify",
										"update-trail"
									]
								}
							},
							"response": []
						},
						{
							"name": "Verify Document: Reject as Invalid",
							"request": {
								"method": "POST",
								"header": [],
								"body": {
									"mode": "raw",
									"raw": "{\n   \"initiatorsystemcode\": \"ABC_WEB_APP\",\n    \"requestorid\": \"REQUESTOR_COGNITO_ID\",\n    \"requestorip\": \"192.168.1.1\",\n    \"documenttype\": \"insurance\",\n    \"documentid\": \"insurance/uploaded/PROVIDER_COGNITO_ID_1/claims/CLAIM_00012345678.PDF\",\n    \"verificationstatus\": \"Rejected\",\n    \"comment\": \"Number does not match\"\n}",
									"options": {
										"raw": {
											"language": "json"
										}
									}
								},
								"url": {
									"raw": "{{API_GATEWAY_URL}}/verify/update-trail",
									"host": [
										"{{API_GATEWAY_URL}}"
									],
									"path": [
										"verify",
										"update-trail"
									]
								}
							},
							"response": []
						}
					]
				}
			]
		}
	],
	"auth": {
		"type": "apikey",
		"apikey": [
			{
				"key": "value",
				"value": "{{API_GATEWAY_KEY}}",
				"type": "string"
			},
			{
				"key": "key",
				"value": "X-API-Key",
				"type": "string"
			}
		]
	},
	"event": [
		{
			"listen": "prerequest",
			"script": {
				"type": "text/javascript",
				"exec": [
					""
				]
			}
		},
		{
			"listen": "test",
			"script": {
				"type": "text/javascript",
				"exec": [
					""
				]
			}
		}
	]
}